kasawa/__init__.py
kasawa/console.py
kasawa/topup.py
kasawa/version.py
kasawa-0.0.5.dist-info/licenses/LICENSE
kasawa-0.0.5.dist-info/METADATA
kasawa-0.0.5.dist-info/WHEEL
kasawa-0.0.5.dist-info/top_level.txt
kasawa-0.0.5.dist-info/RECORD
