Metadata-Version: 2.4
Name: kasawa
Version: 0.0.5
Summary: I Make module this for using for easy to work
Home-page: https://github.com/x2super/kasawa
Author: x2super
Author-email: kasawaonecap@gmail.com
License: MIT
Classifier: License :: OSI Approved :: MIT License
Classifier: Programming Language :: Python :: 3.10
Classifier: Operating System :: OS Independent
Requires-Python: >=3.10
License-File: LICENSE
Requires-Dist: requests
Requires-Dist: cloudscraper
Requires-Dist: pystyle
Dynamic: author
Dynamic: author-email
Dynamic: classifier
Dynamic: description
Dynamic: description-content-type
Dynamic: home-page
Dynamic: license
Dynamic: license-file
Dynamic: requires-dist
Dynamic: requires-python
Dynamic: summary
